cubinlinker/__init__.py
cubinlinker/_nvlinklib.cpython-312-aarch64-linux-gnu.so
cubinlinker/_version.py
cubinlinker/api.py
cubinlinker/patch.py
cubinlinker/tests/__init__.py
cubinlinker/tests/test_device_functions.cubin
cubinlinker/tests/test_device_functions.fatbin
cubinlinker/tests/test_nvlink.py
cubinlinker/tests/test_nvlink_api.py
cubinlinker/tests/test_patch.py
cubinlinker/tests/undefined_extern.cubin
cubinlinker_cu11-0.3.0.post3.dist-info/METADATA
cubinlinker_cu11-0.3.0.post3.dist-info/WHEEL
cubinlinker_cu11-0.3.0.post3.dist-info/top_level.txt
cubinlinker_cu11-0.3.0.post3.dist-info/RECORD
cubinlinker_cu11-0.3.0.post3.dist-info/licenses/LICENSE.txt
