Metadata-Version: 2.4
Name: cubinlinker-cu11
Version: 0.3.0.post3
Summary: Cubin Linker to support Minor Version Compatibility
License: NVIDIA Proprietary Software
License-File: LICENSE.txt
Requires-Dist: ptxcompiler-cu11>=0.7.0
Dynamic: license
Dynamic: license-file
Dynamic: requires-dist
Dynamic: summary
